nonebot_plugin_cfr2/__init__.py
nonebot_plugin_cfr2/config.py
nonebot_plugin_cfr2-0.1.4.dist-info/LICENSE
nonebot_plugin_cfr2-0.1.4.dist-info/METADATA
nonebot_plugin_cfr2-0.1.4.dist-info/WHEEL
nonebot_plugin_cfr2-0.1.4.dist-info/RECORD
