Metadata-Version: 2.1
Name: nonebot-plugin-cfr2
Version: 0.1.4
Summary: Cloudfare R2 customer service plugin, used to connect the R2 storage bucket
License: Apache-2.0
Author: 1v7w
Author-email: 1v7w@gascd.club
Requires-Python: >=3.10,<4.0
Classifier: License :: OSI Approved :: Apache Software License
Classifier: Programming Language :: Python :: 3
Classifier: Programming Language :: Python :: 3.10
Classifier: Programming Language :: Python :: 3.11
Classifier: Programming Language :: Python :: 3.12
Requires-Dist: boto3 (>=1.34.0,<2.0.0)
Requires-Dist: botocore (>=1.34.0,<2.0.0)
Requires-Dist: nonebot2 (>=2.0.0rc4,<3.0.0)
Requires-Dist: requests (>=2.32.0,<3.0.0)
